{
  "treemenu": [
    {
      "Title": "Example menu item level 1",
      "Url": "#",
      "Children": [
        {
          "Title": "Example menu item level 2",
          "Url": "#",
          "Children": [
            {
              "Title": "Example menu item level 3",
              "Url": "#"
            },
            {
              "Title": "Example menu item level ",
              "Url": "#",
              "Children": [
                {
                  "Title": "Example menu item level ",
                  "Url": "#"
                },
                {
                  "Title": "Example menu item level ",
                  "Url": "#",
                  "Children": [
                    {
                      "Title": "Example menu item level ",
                      "Url": "#"
                    },
                    {
                      "Title": "Example menu item level ",
                      "Url": "#"
                    },
                    {
                      "Title": "Example menu item level ",
                      "Url": "#"
                    },
                    {
                      "Title": "Example menu item level ",
                      "Url": "#"
                    },
                    {
                      "Title": "Example menu item level ",
                      "Url": "#"
                    },
                    {
                      "Title": "Example menu item level ",
                      "Url": "#"
                    },
                    {
                      "Title": "Example menu item level ",
                      "Url": "#"
                    }
                  ]
                },
                {
                  "Title": "Example menu item level ",
                  "Url": "#"
                },
                {
                  "Title": "Example menu item level ",
                  "Url": "#"
                },
                {
                  "Title": "Example menu item level ",
                  "Url": "#"
                },
                {
                  "Title": "Example menu item level ",
                  "Url": "#"
                },
                {
                  "Title": "Example menu item level ",
                  "Url": "#"
                },
                {
                  "Title": "Example menu item level ",
                  "Url": "#"
                },
                {
                  "Title": "Example menu item level ",
                  "Url": "#"
                },
                {
                  "Title": "Example menu item level ",
                  "Url": "#"
                },
                {
                  "Title": "Example menu item level ",
                  "Url": "#"
                },
                {
                  "Title": "Example menu item level ",
                  "Url": "#"
                },
                {
                  "Title": "Example menu item level ",
                  "Url": "#"
                },
                {
                  "Title": "Example menu item level ",
                  "Url": "#"
                }
              ]
            },
            {
              "Title": "Example menu item level ",
              "Url": "#"
            },
            {
              "Title": "Example menu item level ",
              "Url": "#"
            },
            {
              "Title": "Example menu item level ",
              "Url": "#"
            },
            {
              "Title": "Example menu item level ",
              "Url": "#",
              "Children": [
                {
                  "Title": "Example menu item level ",
                  "Url": "#"
                },
                {
                  "Title": "Example menu item level ",
                  "Url": "#",
                  "Children": [
                    {
                      "Title": "Example menu item level ",
                      "Url": "#"
                    },
                    {
                      "Title": "Example menu item level ",
                      "Url": "#"
                    },
                    {
                      "Title": "Example menu item level ",
                      "Url": "#"
                    },
                    {
                      "Title": "Example menu item level ",
                      "Url": "#"
                    },
                    {
                      "Title": "Example menu item level ",
                      "Url": "#"
                    },
                    {
                      "Title": "Example menu item level ",
                      "Url": "#"
                    },
                    {
                      "Title": "Example menu item level ",
                      "Url": "#"
                    }
                  ]
                },
                {
                  "Title": "Example menu item level ",
                  "Url": "#"
                },
                {
                  "Title": "Example menu item level ",
                  "Url": "#"
                },
                {
                  "Title": "Example menu item level ",
                  "Url": "#"
                },
                {
                  "Title": "Example menu item level ",
                  "Url": "#"
                },
                {
                  "Title": "Example menu item level ",
                  "Url": "#"
                },
                {
                  "Title": "Example menu item level ",
                  "Url": "#"
                },
                {
                  "Title": "Example menu item level ",
                  "Url": "#"
                },
                {
                  "Title": "Example menu item level ",
                  "Url": "#"
                },
                {
                  "Title": "Example menu item level ",
                  "Url": "#"
                },
                {
                  "Title": "Example menu item level ",
                  "Url": "#"
                },
                {
                  "Title": "Example menu item level ",
                  "Url": "#"
                },
                {
                  "Title": "Example menu item level ",
                  "Url": "#"
                }
              ]
            },
            {
              "Title": "Example menu item level ",
              "Url": "#"
            },
            {
              "Title": "Example menu item level ",
              "Url": "#"
            },
            {
              "Title": "Example menu item level ",
              "Url": "#"
            },
            {
              "Title": "Example menu item level ",
              "Url": "#"
            },
            {
              "Title": "Example menu item level ",
              "Url": "#"
            },
            {
              "Title": "Example menu item level ",
              "Url": "#"
            },
            {
              "Title": "Example menu item level 3",
              "Url": "#",
              "Children": [
                {
                  "Title": "Example menu item level ",
                  "Url": "#"
                },
                {
                  "Title": "Example menu item level ",
                  "Url": "#",
                  "Children": [
                    {
                      "Title": "Example menu item level ",
                      "Url": "#"
                    },
                    {
                      "Title": "Example menu item level ",
                      "Url": "#"
                    },
                    {
                      "Title": "Example menu item level ",
                      "Url": "#"
                    },
                    {
                      "Title": "Example menu item level ",
                      "Url": "#"
                    },
                    {
                      "Title": "Example menu item level ",
                      "Url": "#"
                    },
                    {
                      "Title": "Example menu item level ",
                      "Url": "#"
                    },
                    {
                      "Title": "Example menu item level ",
                      "Url": "#"
                    }
                  ]
                },
                {
                  "Title": "Example menu item level ",
                  "Url": "#"
                },
                {
                  "Title": "Example menu item level ",
                  "Url": "#"
                },
                {
                  "Title": "Example menu item level ",
                  "Url": "#"
                },
                {
                  "Title": "Example menu item level ",
                  "Url": "#"
                },
                {
                  "Title": "Example menu item level ",
                  "Url": "#"
                },
                {
                  "Title": "Example menu item level ",
                  "Url": "#"
                },
                {
                  "Title": "Example menu item level ",
                  "Url": "#"
                },
                {
                  "Title": "Example menu item level ",
                  "Url": "#"
                },
                {
                  "Title": "Example menu item level ",
                  "Url": "#"
                },
                {
                  "Title": "Example menu item level ",
                  "Url": "#"
                },
                {
                  "Title": "Example menu item level ",
                  "Url": "#"
                },
                {
                  "Title": "Example menu item level ",
                  "Url": "#"
                }
              ]
            },
            {
              "Title": "Example menu item level 3",
              "Url": "#"
            },
            {
              "Title": "Example menu item level 3",
              "Url": "#",
              "Children": [
                {
                  "Title": "Example menu item level ",
                  "Url": "#"
                },
                {
                  "Title": "Example menu item level ",
                  "Url": "#"
                },
                {
                  "Title": "Example menu item level ",
                  "Url": "#"
                },
                {
                  "Title": "Example menu item level ",
                  "Url": "#"
                },
                {
                  "Title": "Example menu item level ",
                  "Url": "#",
                  "Children": [
                    {
                      "Title": "Example menu item level ",
                      "Url": "#"
                    },
                    {
                      "Title": "Example menu item level ",
                      "Url": "#"
                    },
                    {
                      "Title": "Example menu item level ",
                      "Url": "#"
                    },
                    {
                      "Title": "Example menu item level ",
                      "Url": "#"
                    },
                    {
                      "Title": "Example menu item level ",
                      "Url": "#"
                    },
                    {
                      "Title": "Example menu item level ",
                      "Url": "#"
                    },
                    {
                      "Title": "Example menu item level ",
                      "Url": "#"
                    }
                  ]
                },
                {
                  "Title": "Example menu item level ",
                  "Url": "#"
                },
                {
                  "Title": "Example menu item level ",
                  "Url": "#"
                },
                {
                  "Title": "Example menu item level ",
                  "Url": "#"
                },
                {
                  "Title": "Example menu item level ",
                  "Url": "#"
                },
                {
                  "Title": "Example menu item level ",
                  "Url": "#"
                },
                {
                  "Title": "Example menu item level ",
                  "Url": "#"
                }
              ]
            }
          ]
        },
        {
          "Title": "Example menu item level 2",
          "Url": "#",
          "Children": [
            {
              "Title": "Example menu item level ",
              "Url": "#"
            },
            {
              "Title": "Example menu item level ",
              "Url": "#"
            },
            {
              "Title": "Example menu item level ",
              "Url": "#"
            },
            {
              "Title": "Example menu item level ",
              "Url": "#"
            }
          ]
        },
        {
          "Title": "Example menu item level 2",
          "Url": "#",
          "Children": [
            {
              "Title": "Example menu item level ",
              "Url": "#"
            },
            {
              "Title": "Example menu item level ",
              "Url": "#"
            },
            {
              "Title": "Example menu item level ",
              "Url": "#"
            },
            {
              "Title": "Example menu item level ",
              "Url": "#"
            },
            {
              "Title": "Example menu item level ",
              "Url": "#"
            },
            {
              "Title": "Example menu item level ",
              "Url": "#"
            },
            {
              "Title": "Example menu item level ",
              "Url": "#"
            }
          ]
        },
        {
          "Title": "Example menu item level 2",
          "Url": "#",
          "Children": [
            {
              "Title": "Example menu item level ",
              "Url": "#"
            },
            {
              "Title": "Example menu item level ",
              "Url": "#"
            },
            {
              "Title": "Example menu item level ",
              "Url": "#"
            },
            {
              "Title": "Example menu item level ",
              "Url": "#"
            },
            {
              "Title": "Example menu item level ",
              "Url": "#"
            },
            {
              "Title": "Example menu item level ",
              "Url": "#"
            },
            {
              "Title": "Example menu item level ",
              "Url": "#"
            }
          ]
        },
        {
          "Title": "Example menu item level ",
          "Url": "#"
        },
        {
          "Title": "Example menu item level ",
          "Url": "#"
        },
        {
          "Title": "Example menu item level ",
          "Url": "#"
        }
      ]
    },
    {
      "Title": "Example menu item level 1",
      "Url": "#"
    },
    {
      "Title": "Example menu item level 1",
      "Url": "#",
      "Children": [
        {
          "Title": "Example menu item level 2",
          "Url": "#"
        },
        {
          "Title": "Example menu item level 2",
          "Url": "#",
          "Children": [
            {
              "Title": "Example menu item level ",
              "Url": "#",
              "Children": [
                {
                  "Title": "Example menu item level ",
                  "Url": "#"
                },
                {
                  "Title": "Example menu item level ",
                  "Url": "#"
                },
                {
                  "Title": "Example menu item level ",
                  "Url": "#"
                },
                {
                  "Title": "Example menu item level ",
                  "Url": "#"
                },
                {
                  "Title": "Example menu item level ",
                  "Url": "#"
                },
                {
                  "Title": "Example menu item level ",
                  "Url": "#"
                },
                {
                  "Title": "Example menu item level ",
                  "Url": "#"
                },
                {
                  "Title": "Example menu item level ",
                  "Url": "#"
                }
              ]
            },
            {
              "Title": "Example menu item level ",
              "Url": "#"
            },
            {
              "Title": "Example menu item level ",
              "Url": "#"
            },
            {
              "Title": "Example menu item level ",
              "Url": "#"
            },
            {
              "Title": "Example menu item level ",
              "Url": "#",
              "Children": [
                {
                  "Title": "Example menu item level ",
                  "Url": "#"
                },
                {
                  "Title": "Example menu item level ",
                  "Url": "#"
                },
                {
                  "Title": "Example menu item level ",
                  "Url": "#"
                },
                {
                  "Title": "Example menu item level ",
                  "Url": "#"
                },
                {
                  "Title": "Example menu item level ",
                  "Url": "#"
                },
                {
                  "Title": "Example menu item level ",
                  "Url": "#"
                },
                {
                  "Title": "Example menu item level ",
                  "Url": "#"
                },
                {
                  "Title": "Example menu item level ",
                  "Url": "#"
                }
              ]              
            },
            {
              "Title": "Example menu item level ",
              "Url": "#"
            },
            {
              "Title": "Example menu item level ",
              "Url": "#"
            }
          ]
        },
        {
          "Title": "Example menu item level 2",
          "Url": "#"
        },
        {
          "Title": "Example menu item level 2",
          "Url": "#"
        }
      ]
    },
    {
      "Title": "Example menu item level 1",
      "Url": "#"
    },
    {
      "Title": "Example menu item level 1",
      "Url": "#",
      "Children": [
        {
          "Title": "Example menu item level ",
          "Url": "#",
          "Children": [
            {
              "Title": "Example menu item level ",
              "Url": "#"
            },
            {
              "Title": "Example menu item level ",
              "Url": "#"
            },
            {
              "Title": "Example menu item level ",
              "Url": "#"
            },
            {
              "Title": "Example menu item level ",
              "Url": "#"
            },
            {
              "Title": "Example menu item level ",
              "Url": "#"
            },
            {
              "Title": "Example menu item level ",
              "Url": "#"
            },
            {
              "Title": "Example menu item level ",
              "Url": "#"
            },
            {
              "Title": "Example menu item level ",
              "Url": "#"
            }
          ]
        },
        {
          "Title": "Example menu item level ",
          "Url": "#"
        },
        {
          "Title": "Example menu item level ",
          "Url": "#"
        },
        {
          "Title": "Example menu item level ",
          "Url": "#"
        },
        {
          "Title": "Example menu item level ",
          "Url": "#"
        },
        {
          "Title": "Example menu item level ",
          "Url": "#",
          "Children": [
            {
              "Title": "Example menu item level ",
              "Url": "#",
              "Children": [
                {
                  "Title": "Example menu item level ",
                  "Url": "#"
                },
                {
                  "Title": "Example menu item level ",
                  "Url": "#"
                },
                {
                  "Title": "Example menu item level ",
                  "Url": "#"
                },
                {
                  "Title": "Example menu item level ",
                  "Url": "#"
                },
                {
                  "Title": "Example menu item level ",
                  "Url": "#"
                },
                {
                  "Title": "Example menu item level ",
                  "Url": "#"
                },
                {
                  "Title": "Example menu item level ",
                  "Url": "#"
                },
                {
                  "Title": "Example menu item level ",
                  "Url": "#"
                }
              ]
            },
            {
              "Title": "Example menu item level ",
              "Url": "#"
            },
            {
              "Title": "Example menu item level ",
              "Url": "#"
            },
            {
              "Title": "Example menu item level ",
              "Url": "#"
            },
            {
              "Title": "Example menu item level ",
              "Url": "#"
            },
            {
              "Title": "Example menu item level ",
              "Url": "#"
            },
            {
              "Title": "Example menu item level ",
              "Url": "#"
            },
            {
              "Title": "Example menu item level ",
              "Url": "#"
            }
          ]
        },
        {
          "Title": "Example menu item level ",
          "Url": "#"
        },
        {
          "Title": "Example menu item level ",
          "Url": "#"
        },
        {
          "Title": "Example menu item level ",
          "Url": "#"
        },
        {
          "Title": "Example menu item level ",
          "Url": "#"
        },
        {
          "Title": "Example menu item level ",
          "Url": "#"
        },
        {
          "Title": "Example menu item level ",
          "Url": "#"
        }
      ]
    },
    {
      "Title": "Example menu item level 1",
      "Url": "#",
      "Children": [
        {
          "Title": "Example menu item level ",
          "Url": "#",
          "Children": [
            {
              "Title": "Example menu item level ",
              "Url": "#"
            },
            {
              "Title": "Example menu item level ",
              "Url": "#"
            },
            {
              "Title": "Example menu item level ",
              "Url": "#"
            },
            {
              "Title": "Example menu item level ",
              "Url": "#"
            },
            {
              "Title": "Example menu item level ",
              "Url": "#"
            },
            {
              "Title": "Example menu item level ",
              "Url": "#"
            },
            {
              "Title": "Example menu item level ",
              "Url": "#"
            },
            {
              "Title": "Example menu item level ",
              "Url": "#"
            }
          ]
        },
        {
          "Title": "Example menu item level ",
          "Url": "#"
        },
        {
          "Title": "Example menu item level ",
          "Url": "#"
        },
        {
          "Title": "Example menu item level ",
          "Url": "#"
        },
        {
          "Title": "Example menu item level ",
          "Url": "#"
        },
        {
          "Title": "Example menu item level ",
          "Url": "#"
        },
        {
          "Title": "Example menu item level ",
          "Url": "#"
        },
        {
          "Title": "Example menu item level ",
          "Url": "#"
        }
      ]
    },
    {
      "Title": "Example menu item level 1",
      "Url": "#",
      "Children": [
        {
          "Title": "Example menu item level ",
          "Url": "#",
          "Children": [
            {
              "Title": "Example menu item level ",
              "Url": "#"
            },
            {
              "Title": "Example menu item level ",
              "Url": "#"
            },
            {
              "Title": "Example menu item level ",
              "Url": "#"
            },
            {
              "Title": "Example menu item level ",
              "Url": "#"
            },
            {
              "Title": "Example menu item level ",
              "Url": "#"
            },
            {
              "Title": "Example menu item level ",
              "Url": "#"
            },
            {
              "Title": "Example menu item level ",
              "Url": "#"
            },
            {
              "Title": "Example menu item level ",
              "Url": "#"
            }
          ]
        },
        {
          "Title": "Example menu item level ",
          "Url": "#"
        },
        {
          "Title": "Example menu item level ",
          "Url": "#"
        },
        {
          "Title": "Example menu item level ",
          "Url": "#"
        }
      ]
    },
    {
      "Title": "Example menu item level 1",
      "Url": "#"
    },
    {
      "Title": "Example menu item level 1",
      "Url": "#",
      "Children": [
        {
          "Title": "Example menu item level ",
          "Url": "#"
        },
        {
          "Title": "Example menu item level ",
          "Url": "#"
        },
        {
          "Title": "Example menu item level ",
          "Url": "#"
        },
        {
          "Title": "Example menu item level ",
          "Url": "#"
        },
        {
          "Title": "Example menu item level ",
          "Url": "#"
        },
        {
          "Title": "Example menu item level ",
          "Url": "#"
        },
        {
          "Title": "Example menu item level ",
          "Url": "#"
        },
        {
          "Title": "Example menu item level ",
          "Url": "#"
        }
      ]
    },
    {
      "Title": "Example menu item level 1",
      "Url": "#"
    }
  ]
}
